setup.py
Flask_SockJS.egg-info/PKG-INFO
Flask_SockJS.egg-info/SOURCES.txt
Flask_SockJS.egg-info/dependency_links.txt
Flask_SockJS.egg-info/not-zip-safe
Flask_SockJS.egg-info/requires.txt
Flask_SockJS.egg-info/top_level.txt
flask_sockjs/__init__.py
flask_sockjs/endpoint.py