Metadata-Version: 1.1
Name: Flask-SockJS
Version: 0.1.0
Summary: Simple integration of Flask and SockJS
Home-page: http://github.com/cravler/flask-sockjs/
Author: Sergei Vizel
Author-email: sergei.vizel@gmail.com
License: MIT
Platform: any
Classifier: Environment :: Web Environment
Classifier: Intended Audience :: Developers
Classifier: License :: OSI Approved :: MIT License
Classifier: Operating System :: OS Independent
Classifier: Programming Language :: Python
Classifier: Topic :: Internet :: WWW/HTTP :: Dynamic Content
Classifier: Topic :: Software Development :: Libraries :: Python Modules
